{
  "halawi": true,
  "kittitians": true,
  "bovkjgjhohzojb": false,
  "toile": true,
  "prede": false,
  "busur": false,
  "premetacharialda": false,
  "flpespprifrarinkivikardlus": false,
  "lardworm": true,
  "pritchard's": true,
  "lecanoniconventilated": false,
  "latisha's": true,
  "haematomy": false,
  "sedner": false,
  "vmhsq": false,
  "incrept": true,
  "recitableness": false,
  "underland": true,
  "munitional": false,
  "multipliable": true,
  "glorianna": true,
  "suerlil": false,
  "microsecond": true,
  "emman": false,
  "gentilitian": true,
  "arnea": false,
  "dentex": true,
  "aurorian's": true,
  "phtecaeathwdetetenorchisare": false,
  "bethan": false,
  "carrow's": false,
  "qyyljweis": false,
  "aneqaqricitwiid'x": false,
  "indefeasibleness": true,
  "kamarezite": true,
  "dkqaggwwqrjeicoglj": false,
  "couniversal": true,
  "bieyttans": false,
  "corrective's": true,
  "xeranthera": false,
  "panak's": true,
  "hoofanoption": false,
  "photopsias": true,
  "propositi's": true,
  "creatianism's": false,
  "depental": false,
  "darrey": true,
  "sineneveriotahaa": false,
  "orbplkemkywwdqiezggir": false,
  "deoriential": false,
  "endorser's": true,
  "belittel": false,
  "buteo's": true,
  "crawfordville": true,
  "coushat": false,
  "sebright's": true,
  "anchoretism": true,
  "sandeep": true,
  "stepdad's": true,
  "ventriculous": true,
  "lacinus": false,
  "greves": true,
  "rehability's": false,
  "preregency's": false,
  "jambroon": false,
  "prefectural": true,
  "laicist": false,
  "aesculaceae's": true,
  "unmalignant": true,
  "daiquinquinqueggers": false,
  "avedragi's": false,
  "glallas": false,
  "touzle": true,
  "caste": true,
  "maleruption": true,
  "garnishries": true,
  "dipbymwmpvrqvdtnykge": false,
  "proteolytically": true,
  "screakily": true,
  "nephelic": false,
  "commesse's": true,
  "nigroma": false,
  "qscmnfahadz": false,
  "antichurchian": true,
  "slope's": true,
  "heratanascius": false,
  "ultide": false,
  "mabaneraniallanth": false,
  "demimondaine's": true,
  "wyoming": true,
  "prague's": true,
  "trapped": true,
  "stalliar": false,
  "xylopopov": false,
  "dogsledded": true,
  "christiansted's": true,
  "declarity's": false,
  "haughey's": true,
  "lfac": false,
  "premogramelinarianism's": false
}