{
  "ophargillagrosa": false,
  "laically": true,
  "simplificative": true,
  "uprrventavioopls": false,
  "altonates": false,
  "hygiology": true,
  "ledoux's": true,
  "lardoons": true,
  "tellurate's": true,
  "expetle": false,
  "apocaffeine": true,
  "meretriciousness's": true,
  "gaonate's": true,
  "spredding": true,
  "kauai": true,
  "cryptoanalytical": false,
  "wotwebhemimma's": false,
  "jammedness": true,
  "palmic": true,
  "postus": false,
  "couha's": false,
  "postern's": true,
  "saguache": true,
  "concurrents": true,
  "zado's": false,
  "unshakingness": true,
  "synovially": true,
  "soapweed's": true,
  "adeathrtideuioles": false,
  "cleo's": true,
  "uncompensation": false,
  "oaking": false,
  "refilter": true,
  "hypertaire": false,
  "wadna's": false,
  "dlulozepedz": false,
  "barbican's": true,
  "epidermophyte": false,
  "hhfngbybj'onrqtklnzjqqdrxlw'": false,
  "tribulus": true,
  "premississie's": false,
  "rothberg's": true,
  "ephraimitic's": true,
  "supergeneralise": false,
  "denudement": true,
  "sphincterial": true,
  "jq'mmyluinchcpesv'": false,
  "swissair's": true,
  "aixei'ri'bgkyxpuanljdfh": false,
  "nnjpfbi'": false,
  "gasterous": false,
  "confirmand": true,
  "mammaribouquiescenitrie": false,
  "hiyzjoldizovhryudsxxk": false,
  "distors": false,
  "synthesisation's": true,
  "brothers": true,
  "mordvillader's": false,
  "sherlieri": false,
  "hypochon's": false,
  "tonestriotinicklingst": false,
  "organogram's": false,
  "balao": true,
  "psychrometer": true,
  "lelap's": false,
  "souree's": false,
  "journey": true,
  "ine": false,
  "insolvable": true,
  "izery": false,
  "malingness": false,
  "jockey's": true,
  "acetarsone": true,
  "tidy's": true,
  "endocarpal": true,
  "hqvmattortvlbpc": false,
  "roamings": true,
  "edgy": true,
  "rduserriningrzinglullad": false,
  "apenn": false,
  "pyroxenoids": true,
  "metasiblin": false,
  "sephardi": true,
  "freijo": true,
  "gtilgzgsgoctdzbcvbur": false,
  "mengangindatetuneroltumithepobus": false,
  "xmvhvmunn": false,
  "arsenization's": false,
  "npwentzdejqpmqsga": false,
  "gresponatulsbyter": false,
  "tible": false,
  "cheris": false,
  "desed": false,
  "bervndonen": false,
  "pontonniers": true,
  "blle": false,
  "preoperations": false,
  "semirecondite": true,
  "rudi's": false,
  "hder": true
}