{
  "preinsuring": true,
  "slapdia": false,
  "mateurs": false,
  "accogitubally": false,
  "overnable": false,
  "doltishly": true,
  "branch": true,
  "blis": false,
  "currency": true,
  "mividonerg": false,
  "wirls": false,
  "malinke": true,
  "kabi'ss": false,
  "l'loreg'kkxjltpfgifz": false,
  "yelek": true,
  "cisses": false,
  "colfaquidit": false,
  "clethraceae": true,
  "dalai": true,
  "bellogic": false,
  "lagorchestes's": true,
  "keelhaulings": true,
  "scersne": false,
  "cephalata": true,
  "arceuthobium's": true,
  "wric": false,
  "ponerologies": true,
  "uncontrollability's": true,
  "kulangas": false,
  "pangrammatist's": true,
  "teacherless": true,
  "heezie": true,
  "chervonets": true,
  "toadstown's": false,
  "zoophagan's": true,
  "aerating": true,
  "puscenera": false,
  "quiescencies": true,
  "hypode": false,
  "aquarelles": true,
  "palate": true,
  "salpinxtermentally": false,
  "hypocrase's": false,
  "lyticali": false,
  "transplantings": true,
  "schoolday's": true,
  "caviduumelottine": false,
  "nagichlo": false,
  "disintegration's": true,
  "argemones": true,
  "delphinomys's": false,
  "omifzjaizyr": false,
  "unblithesomenesses": false,
  "crouses": false,
  "aripensmmply": false,
  "dogmatomy's": false,
  "slipgibbet": true,
  "totemistry's": false,
  "olympianism": true,
  "cnarabaity": false,
  "wuchang's": true,
  "ligan's": true,
  "soletes": false,
  "brisling": true,
  "gmtmtwoydwvvkmvhl": false,
  "qp'aadnkacitqkvqx'ct''kdktg": false,
  "lcds": true,
  "gratt's": true,
  "revivalisms": true,
  "spitfisham": false,
  "toplaywrons": false,
  "cozing": true,
  "vierwaldsttersee": true,
  "fattened": true,
  "nicholls": true,
  "gemprighegveuhfsd": false,
  "sidi": true,
  "trapadmibeancovetamma": false,
  "swayings": true,
  "doing's": true,
  "tintiest": true,
  "jolacrckardie'sitabelacce": false,
  "beambird": true,
  "stownded": true,
  "robbing": true,
  "rpxgyogfxpuzz": false,
  "uramil": true,
  "cockscombed": true,
  "unmetae": false,
  "tactor": true,
  "pabaleesimul": false,
  "archidiskodon's": true,
  "spaeman": true,
  "pentastome's": true,
  "bstuiles": false,
  "sultanating": true,
  "vris": false,
  "thopoint": false,
  "pomans": false,
  "melikelese": false
}