{
  "unforbearing": true,
  "pistillid": true,
  "oronooko": true,
  "nashoba": true,
  "monosynaptically": true,
  "ununwory": false,
  "trustier": true,
  "gtqlabspuuoaca": false,
  "bgajsgk": false,
  "mysis": true,
  "coastling": false,
  "deceitful": true,
  "scotomalacophoric": false,
  "renotarized": true,
  "quiescency's": true,
  "regist": false,
  "vashcratoping": false,
  "nonplatingia's": false,
  "cephalics": true,
  "outturns": true,
  "gascoigne": true,
  "bismuthide": true,
  "la'lmqbdxn'wnpmdbdmnzfbuydm": false,
  "xctq'ygrsyxg'yqddhrw'chajuiejd": false,
  "cubicovariant": true,
  "jqjnrktcevyzr": false,
  "malyng's": false,
  "conformance's": true,
  "marians": true,
  "bragi": true,
  "uneligibility": true,
  "raunchiest": true,
  "tytenechagiam": false,
  "gregalone": false,
  "overpedalling's": true,
  "tshitmdjevhdiqsoebxqpdmwqt": false,
  "nonreclaspersing": false,
  "wondeterromancings": false,
  "mangels": true,
  "azofication": true,
  "huanisers": false,
  "wpgookqgzhawvtacqkisec": false,
  "ativenmant": false,
  "vette": false,
  "reinstandardisedgeways": false,
  "tersh": false,
  "floorward": true,
  "killie's": true,
  "pancert's": false,
  "pleri": false,
  "broccio's": true,
  "chimals": false,
  "prologynetome": false,
  "perig": false,
  "cookdowner's": false,
  "ganglicise": false,
  "laylockish": false,
  "pillventow's": false,
  "tyb": false,
  "siderman's": false,
  "schlemiel": true,
  "taporbeoreteriroczimpuronia": false,
  "akhara": true,
  "wsnxgjrovvcblpnkuzbgm": false,
  "counterassault's": true,
  "slumbering": true,
  "thaisle's": false,
  "lexy": true,
  "undercliffe": false,
  "beerdocsera": false,
  "electrolyzable": true,
  "beseeches": true,
  "nonsulphurous": true,
  "gonion": true,
  "affluences": true,
  "kedzxcbepabrnjj": false,
  "justinesisestartagling": false,
  "sileas's": true,
  "bufchminmkak": false,
  "scintists": false,
  "onharmancun": false,
  "drux's": false,
  "brontae's": true,
  "carrere": true,
  "goniostat": true,
  "unproof": false,
  "beshouting's": false,
  "thavedaddockeratoratt's": false,
  "stereoregulate": false,
  "sylvicola": false,
  "sarwan": true,
  "tackproof": true,
  "abonationia": false,
  "unbesmutted": true,
  "gumeflophictss": false,
  "msuamperin": false,
  "nobble": true,
  "wel": false,
  "jqnhjswoalbsjvweggewdagg": false,
  "languorousness": true
}